unipack/__init__.py
unipack/uniprot.py
unipack/uniprot_collection.py
unipack-0.1.4.dist-info/METADATA
unipack-0.1.4.dist-info/WHEEL
unipack-0.1.4.dist-info/top_level.txt
unipack-0.1.4.dist-info/RECORD
