Metadata-Version: 2.1
Name: unipack
Version: 0.1.4
Summary: Add your description here
Requires-Python: >=3.10
Requires-Dist: matplotlib>=3.9.2
